cenplot/__init__.py
cenplot/main.py
cenplot/cli/draw.py
cenplot/lib/__init__.py
cenplot/lib/defaults.py
cenplot/lib/utils.py
cenplot/lib/draw/__init__.py
cenplot/lib/draw/bar.py
cenplot/lib/draw/core.py
cenplot/lib/draw/hor.py
cenplot/lib/draw/label.py
cenplot/lib/draw/legend.py
cenplot/lib/draw/line.py
cenplot/lib/draw/local_self_ident.py
cenplot/lib/draw/self_ident.py
cenplot/lib/draw/settings.py
cenplot/lib/draw/strand.py
cenplot/lib/draw/utils.py
cenplot/lib/io/__init__.py
cenplot/lib/io/bed9.py
cenplot/lib/io/bed_hor.py
cenplot/lib/io/bed_identity.py
cenplot/lib/io/bed_label.py
cenplot/lib/io/tracks.py
cenplot/lib/io/utils.py
cenplot/lib/track/__init__.py
cenplot/lib/track/settings.py
cenplot/lib/track/types.py
cenplot-0.1.4.dist-info/licenses/LICENSE
cenplot-0.1.4.dist-info/METADATA
cenplot-0.1.4.dist-info/WHEEL
cenplot-0.1.4.dist-info/entry_points.txt
cenplot-0.1.4.dist-info/top_level.txt
cenplot-0.1.4.dist-info/RECORD
