Metadata-Version: 2.4
Name: cenplot
Version: 0.1.4
Summary: Centromere plotting library.
Author-email: Keith Oshima <oshimak@pennmedicine.upenn.edu>
License: MIT License
Project-URL: Homepage, https://github.com/logsdon-lab/cenplot
Requires-Python: >=3.12
License-File: LICENSE
Requires-Dist: matplotlib>=3.10.0
Requires-Dist: polars>=1.19.0
Requires-Dist: numpy>=2.2.1
Requires-Dist: intervaltree>=3.1.0
Requires-Dist: censtats>=0.0.13
Requires-Dist: PyYAML>=6.0.2
Dynamic: license-file
